[{"artifact_rarity":5,"artifact_type":"Plume of Death","main_stat":"atk","sub_stats":[{"name":"def","value":"16"},{"name":"hp","value":"239"},{"name":"crit dmg%","value":"7.8"}],"enhance":[{"name":"hp%","value":"4.1"}],"id":"6bb939fe-d99d-42e1-945e-f9552bbc8b2a"},{"artifact_rarity":1,"artifact_type":"Plume of Death","main_stat":"atk","sub_stats":[],"enhance":[{"name":"hp%","value":"1.2"}],"id":"58b51502-ad9c-4205-a910-3aa330d0b7b4"},{"artifact_rarity":1,"artifact_type":"Flower of Life","main_stat":"hp","sub_stats":[],"enhance":[{"name":"atk%","value":"1.5"}],"id":"a5a9a93a-65c6-4271-afd7-8d14db2db8ea"},{"artifact_rarity":5,"artifact_type":"Plume of Death","main_stat":"atk","sub_stats":[{"name":"def","value":"23"},{"name":"crit dmg%","value":"6.2"},{"name":"crit rate%","value":"3.5"}],"enhance":[{"name":"hp%","value":"4.1"}],"id":"58ea5d9c-77e4-45c3-805a-e491847423ec"},{"artifact_rarity":1,"artifact_type":"Flower of Life","main_stat":"hp","sub_stats":[],"enhance":[{"name":"atk%","value":"1.2"}],"id":"e62f2d4f-4a9e-446f-8859-54c3be55bbb8"},{"artifact_rarity":5,"artifact_type":"Flower of Life","main_stat":"hp","sub_stats":[{"name":"atk","value":"29"},{"name":"elemental mastery","value":"23"},{"name":"atk%","value":"5.8"},{"name":"hp%","value":"4.7"}],"enhance":[{"name":"elemental mastery","value":17}],"id":"e908b401-1832-45a8-971c-821a3e3ab146"},{"artifact_rarity":5,"artifact_type":"Sands of Eon","main_stat":"hp%","sub_stats":[{"name":"energy recharge","value":"6.5"},{"name":"elemental mastery","value":"42"},{"name":"hp","value":"299"},{"name":"atk","value":"31"}],"enhance":[{"name":"elemental mastery","value":19},{"name":"atk","value":16}],"id":"32212249-c911-471f-b45e-1e52bbd99f9d"},{"artifact_rarity":1,"artifact_type":"Flower of Life","main_stat":"hp","sub_stats":[],"enhance":[{"name":"def%","value":"1.8"}],"id":"73084aaa-6b4b-447c-a68a-6c7afe1f3ec8"},{"artifact_rarity":5,"artifact_type":"Sands of Eon","main_stat":"energy recharge","sub_stats":[{"name":"def%","value":"6.6"},{"name":"atk","value":"19"},{"name":"hp%","value":"4.7"},{"name":"def","value":"21"}],"enhance":[{"name":"def%","value":5.1}],"id":"41961330-28b6-4665-82cf-9eb6fd4f92c6"},{"artifact_rarity":5,"artifact_type":"Sands of Eon","main_stat":"energy recharge","sub_stats":[{"name":"def%","value":"11.7"},{"name":"atk","value":"19"},{"name":"hp%","value":"4.7"},{"name":"def","value":"21"}],"enhance":[{"name":"atk","value":20}],"id":"c6af7a32-e444-4b77-b91e-ddbed476dd20"},{"artifact_rarity":5,"artifact_type":"Plume of Death","main_stat":"atk","sub_stats":[{"name":"def","value":"23"},{"name":"crit dmg%","value":"6.2"},{"name":"crit rate%","value":"3.5"},{"name":"hp%","value":"4.1"}],"enhance":[{"name":"crit rate%","value":3.5}],"id":"1a5ed6fd-852d-450a-bcc3-c34610c69b8c"},{"artifact_rarity":5,"artifact_type":"Plume of Death","main_stat":"atk","sub_stats":[{"name":"def","value":"23"},{"name":"crit dmg%","value":"6.2"},{"name":"crit rate%","value":"7"},{"name":"hp%","value":"4.1"}],"enhance":[{"name":"crit dmg%","value":6.2},{"name":"crit rate%","value":3.0999999999999996}],"id":"5e7fd740-8e68-436e-9299-31b0b8e85dfc"},{"artifact_rarity":5,"artifact_type":"Circlet of Logos","main_stat":"crit dmg%","sub_stats":[{"name":"hp%","value":"5.8"},{"name":"atk","value":"14"},{"name":"def%","value":"7.3"}],"enhance":[{"name":"def","value":"16"}],"id":"60cabb5d-c0a2-4c86-8918-0744c1b25c1c"},{"artifact_rarity":5,"artifact_type":"Circlet of Logos","main_stat":"crit dmg%","sub_stats":[{"name":"atk","value":"16"},{"name":"elemental mastery","value":"21"},{"name":"energy recharge","value":"5.8"}],"enhance":[{"name":"def%","value":"7.3"}],"id":"7cdfe356-b647-4bd7-9776-ed300f34248e"},{"artifact_rarity":5,"artifact_type":"Circlet of Logos","main_stat":"hp%","sub_stats":[{"name":"def","value":"21"},{"name":"atk","value":"19"},{"name":"crit rate%","value":"3.9"}],"enhance":[{"name":"energy recharge","value":"4.5"}],"id":"93835a5a-f3fc-4602-8cca-4d6f4f33277f"},{"artifact_rarity":5,"artifact_type":"Circlet of Logos","main_stat":"atk%","sub_stats":[{"name":"crit rate%","value":"3.5"},{"name":"elemental mastery","value":"21"},{"name":"atk","value":"16"}],"enhance":[{"name":"crit dmg%","value":"5.4"}],"id":"e933a0a1-2348-4308-95b9-21d3b6195ef5"},{"artifact_rarity":5,"artifact_type":"Circlet of Logos","main_stat":"healing bonus%","sub_stats":[{"name":"def%","value":"6.6"},{"name":"hp","value":"269"},{"name":"crit rate%","value":"3.1"}],"enhance":[{"name":"atk","value":"14"}],"id":"c3eb2a6a-830d-4c2c-b754-24882d2c2593"},{"artifact_rarity":1,"artifact_type":"Flower of Life","main_stat":"hp","sub_stats":[],"enhance":[{"name":"elemental mastery","value":"6"}],"id":"476c0539-bf48-4803-967c-22ad3a818ec4"},{"artifact_rarity":3,"artifact_type":"Circlet of Logos","main_stat":"crit dmg%","sub_stats":[{"name":"crit rate%","value":"1.9"}],"enhance":[{"name":"elemental mastery","value":"14"}],"id":"38cc8130-d335-4966-8eb4-c78f79c97009"},{"artifact_rarity":5,"artifact_type":"Plume of Death","main_stat":"atk","sub_stats":[{"name":"def","value":"23"},{"name":"crit dmg%","value":"12.4"},{"name":"crit rate%","value":"10.1"},{"name":"hp%","value":"4.1"}],"enhance":[{"name":"def","value":23}],"id":"0ebb90aa-1b11-476d-a3f0-961854348f62"},{"artifact_rarity":5,"artifact_type":"Sands of Eon","main_stat":"hp%","sub_stats":[{"name":"atk%","value":"5.3"},{"name":"def","value":"16"},{"name":"energy recharge","value":"5.8"},{"name":"elemental mastery","value":"19"}],"enhance":[{"name":"atk%","value":5.2}],"id":"fc90f6c5-7d63-43d2-933a-f1bf763cd1b4"},{"artifact_rarity":5,"artifact_type":"Circlet of Logos","main_stat":"crit rate%","sub_stats":[{"name":"def","value":"16"},{"name":"atk","value":"16"},{"name":"crit dmg%","value":"7"},{"name":"hp","value":"239"}],"enhance":[{"name":"hp","value":239}],"id":"1572b195-9e77-43bc-90bc-c075478ccb02"},{"artifact_rarity":1,"artifact_type":"Circlet of Logos","main_stat":"def%","sub_stats":[],"enhance":[{"name":"elemental mastery","value":"5"}],"id":"d9df5e7e-a36d-4046-ae4a-227bd66845fa"},{"artifact_rarity":1,"artifact_type":"Goblet of Eonothem","main_stat":"hp%","sub_stats":[],"enhance":[{"name":"atk%","value":"1.2"}],"id":"bb1b0786-affb-4df1-8b98-d9c8ced47788"},{"artifact_rarity":5,"artifact_type":"Sands of Eon","main_stat":"hp%","sub_stats":[{"name":"atk%","value":"10.5"},{"name":"def","value":"16"},{"name":"energy recharge","value":"5.8"},{"name":"elemental mastery","value":"19"}],"enhance":[{"name":"elemental mastery","value":18}],"id":"48bb4f02-19af-4aea-97a0-61ddafe2eb71"},{"artifact_rarity":5,"artifact_type":"Circlet of Logos","main_stat":"crit rate%","sub_stats":[{"name":"def","value":"16"},{"name":"atk","value":"16"},{"name":"crit dmg%","value":"7"},{"name":"hp","value":"478"}],"enhance":[{"name":"hp","value":299}],"id":"f28ec843-080f-4865-8fcd-40b325f8a8a3"},{"artifact_rarity":5,"artifact_type":"Circlet of Logos","main_stat":"def%","sub_stats":[{"name":"atk","value":"14"},{"name":"energy recharge","value":"4.5"},{"name":"hp","value":"299"},{"name":"hp%","value":"4.1"}],"enhance":[{"name":"atk","value":35}],"id":"d24a2a23-48b4-48a4-b2d2-d5850758601a"},{"artifact_rarity":5,"artifact_type":"Circlet of Logos","main_stat":"def%","sub_stats":[{"name":"atk","value":"49"},{"name":"energy recharge","value":"4.5"},{"name":"hp","value":"299"},{"name":"hp%","value":"4.1"}],"enhance":[{"name":"hp","value":269}],"id":"2036e159-277c-4958-a684-bbad345aef98"},{"artifact_rarity":5,"artifact_type":"Circlet of Logos","main_stat":"def%","sub_stats":[{"name":"atk","value":"49"},{"name":"energy recharge","value":"4.5"},{"name":"hp","value":"568"},{"name":"hp%","value":"4.1"}],"enhance":[{"name":"hp","value":239}],"id":"e3a3d496-68d7-4795-9582-1c8a45b07ab4"},{"artifact_rarity":5,"artifact_type":"Circlet of Logos","main_stat":"crit dmg%","sub_stats":[{"name":"hp","value":"299"},{"name":"atk%","value":"4.1"},{"name":"elemental mastery","value":"21"},{"name":"hp%","value":"5.8"}],"enhance":[{"name":"hp%","value":5.3}],"id":"0931edc7-8808-43c4-a0e6-0b44efe0e67e"},{"artifact_rarity":5,"artifact_type":"Sands of Eon","main_stat":"hp%","sub_stats":[{"name":"def","value":"21"},{"name":"energy recharge","value":"5.8"},{"name":"atk","value":"18"}],"enhance":[{"name":"hp","value":"299"}],"id":"d7b4e5ef-a284-4ef0-b8dc-43f055a822c1"},{"artifact_rarity":5,"artifact_type":"Circlet of Logos","main_stat":"crit dmg%","sub_stats":[{"name":"hp","value":"299"},{"name":"atk%","value":"4.1"},{"name":"elemental mastery","value":"21"},{"name":"hp%","value":"11.1"}],"enhance":[{"name":"atk%","value":5.200000000000001}],"id":"9f7c9c6b-7b63-4aad-b716-b6346cad1c18"},{"artifact_rarity":5,"artifact_type":"Circlet of Logos","main_stat":"crit rate%","sub_stats":[{"name":"def","value":"16"},{"name":"atk","value":"16"},{"name":"crit dmg%","value":"7"},{"name":"hp","value":"777"}],"enhance":[{"name":"def","value":19},{"name":"crit dmg%","value":7}],"id":"b4b2b35e-c2a6-4d08-b8cc-4635a89139ee"}]