[{"description":"recharge","type":"20","id":"15d84e25-424d-4549-95fe-631bff3c95af","created":"Sat Feb 05 2022 20:25:15 GMT-0500","artifacts":[{"rarity":5,"type":"Circlet of Logos","main_stat":"def%","sub_stats":[{"stat":"atk%","value":5.3},{"stat":"crit rate%","value":3.9},{"stat":"energy recharge","value":6.5}],"id":"50d6c5a0-6d38-48c7-8659-6a6c87b9a2fa"},{"rarity":4,"type":"Circlet of Logos","main_stat":"crit dmg%","sub_stats":[{"stat":"atk%","value":4.7},{"stat":"hp","value":215},{"stat":"def%","value":4.1}],"id":"e9aa0cd7-64e0-48a2-8289-6e159afc5faa"},{"rarity":4,"type":"Sands of Eon","main_stat":"atk%","sub_stats":[{"stat":"hp","value":239},{"stat":"def%","value":5.3}],"id":"bfde78cf-036b-48ae-a7ee-00c89311f1a5"},{"rarity":4,"type":"Circlet of Logos","main_stat":"hp%","sub_stats":[{"stat":"elemental mastery","value":13},{"stat":"hp","value":239},{"stat":"atk","value":11}],"id":"57150f4e-ecff-444b-a4bc-3c96404c3f7b"},{"rarity":3,"type":"Goblet of Eonothem","main_stat":"atk%","sub_stats":[{"stat":"elemental mastery","value":14},{},{},{}],"id":"16de81a7-7d52-4f0f-a04a-fc8aa3efb416"},{"rarity":3,"type":"Sands of Eon","main_stat":"hp%","sub_stats":[{"stat":"atk","value":7}],"id":"d0cf0c0f-e48d-4742-857c-155d2947cd06"},{"rarity":3,"type":"Plume of Death","main_stat":"atk","sub_stats":[{"stat":"hp%","value":2.5},{"stat":"def","value":11}],"id":"1572c420-2c05-4fab-8c66-b7fbce04af95"}]},{"description":"recharge","type":"condensed","id":"ab81f27e-9767-47a9-909e-6aee1704b175","created":"Sat Feb 05 2022 20:28:20 GMT-0500","artifacts":[{"rarity":5,"type":"Sands of Eon","main_stat":"def%","sub_stats":[{"stat":"crit rate%","value":3.5},{"stat":"hp","value":209},{"stat":"atk","value":16},{"stat":"energy recharge","value":6.5}],"id":"25fdbb98-5cd4-421e-98df-2b2fe3645c38"},{"rarity":5,"type":"Goblet of Eonothem","main_stat":"atk%","sub_stats":[{"stat":"atk","value":16},{"stat":"crit dmg%","value":7},{"stat":"crit rate%","value":3.1}],"id":"e2249b52-0bf2-416a-bb6d-b46ed06f9f26"},{"rarity":4,"type":"Goblet of Eonothem","main_stat":"hp%","sub_stats":[{"stat":"hp","value":167},{"stat":"def%","value":5.8}],"id":"9a4d68b8-5109-43cd-8fbf-537c85c2047a"},{"rarity":4,"type":"Goblet of Eonothem","main_stat":"def%","sub_stats":[{"stat":"atk","value":11},{"stat":"hp","value":167}],"id":"257775c7-3802-4d73-81a4-f2ec38758e1d"},{"rarity":4,"type":"Sands of Eon","main_stat":"hp%","sub_stats":[{"stat":"def","value":15},{"stat":"def%","value":4.1}],"id":"a93659e3-eb4e-408b-bfa6-1984adb96618"},{"rarity":4,"type":"Goblet of Eonothem","main_stat":"hp%","sub_stats":[{"stat":"hp","value":191},{"stat":"def","value":15}],"id":"78e50f4b-314c-4bee-a73a-bfb44386bf7a"},{"rarity":4,"type":"Goblet of Eonothem","main_stat":"atk%","sub_stats":[{"stat":"def%","value":5.8},{"stat":"def","value":13}],"id":"ae644a25-cd5a-4d06-9052-ddb20c62b034"},{"rarity":3,"type":"Plume of Death","main_stat":"atk","sub_stats":[{"stat":"atk%","value":3.2}],"id":"69b2a79f-4cfd-4cdd-b258-ff7a7f946958"},{"rarity":3,"type":"Sands of Eon","main_stat":"def%","sub_stats":[{"stat":"def","value":8}],"id":"dbe2c613-4c92-4448-b7ec-858e014b0e6d"},{"rarity":3,"type":"Goblet of Eonothem","main_stat":"def%","sub_stats":[{"stat":"atk%","value":2.5}],"id":"fbdc7c92-77df-4f6f-9d64-555eeb8b238e"},{"rarity":3,"type":"Goblet of Eonothem","main_stat":"def%","sub_stats":[{"stat":"hp","value":129}],"id":"2a871734-d075-4faa-b81b-9cc732be8481"},{"rarity":3,"type":"Plume of Death","main_stat":"atk","sub_stats":[{"stat":"elemental mastery","value":10},{"stat":"energy recharge","value":3.5}],"id":"96cdb844-79f6-4586-a62e-b33ad6ee0d53"},{"rarity":3,"type":"Circlet of Logos","main_stat":"crit rate%","sub_stats":[{"stat":"def%","value":3.5}],"id":"4d6bea02-7247-46fb-a31b-f46b1f968938"},{"rarity":3,"type":"Flower of Life","main_stat":"hp","sub_stats":[{"stat":"def%","value":4.4}],"id":"8a25d4bd-3534-405f-8b67-4bf26922f1fd"}]},{"description":"recharge","type":"20","id":"d931457d-465b-4f96-9e84-1a68afdf510a","created":"Sat Feb 05 2022 20:31:31 GMT-0500","artifacts":[{"rarity":5,"type":"Plume of Death","main_stat":"atk","sub_stats":[{"stat":"def","value":16},{"stat":"atk%","value":4.1},{"stat":"def%","value":5.1}],"id":"6d47e03d-eb8e-46bb-9f0a-8b3733c72076"},{"rarity":5,"type":"Circlet of Logos","main_stat":"crit dmg%","sub_stats":[{"stat":"crit rate%","value":3.5},{"stat":"elemental mastery","value":19},{"stat":"atk","value":18},{"stat":"hp","value":299}],"id":"b1953eb8-2543-4d4b-b115-0e2bb27e942e"},{"rarity":4,"type":"Goblet of Eonothem","main_stat":"def%","sub_stats":[{"stat":"energy recharge","value":3.6},{"stat":"atk","value":16},{"stat":"hp%","value":4.2}],"id":"80615258-4c88-4f11-80b8-07eca5b01744"},{"rarity":4,"type":"Sands of Eon","main_stat":"elemental mastery","sub_stats":[{"stat":"hp","value":191},{"stat":"hp%","value":3.7}],"id":"944ef4d0-e5da-4915-969b-a86e4079b2d3"},{"rarity":4,"type":"Goblet of Eonothem","main_stat":"hp%","sub_stats":[{"stat":"elemental mastery","value":13},{"stat":"hp","value":167},{"stat":"atk","value":16}],"id":"d7c4f10e-3863-489f-9d2b-a83880a5676e"},{"rarity":4,"type":"Circlet of Logos","main_stat":"atk%","sub_stats":[{"stat":"def%","value":4.1},{"stat":"hp%","value":4.7}],"id":"af2fb701-b920-4862-bc45-159096aae9fe"},{"rarity":3,"type":"Goblet of Eonothem","main_stat":"elemental mastery","sub_stats":[{"stat":"def","value":8}],"id":"d9521410-2d8a-4e36-a55e-c2237b404ebb"},{"rarity":3,"type":"Plume of Death","main_stat":"atk","sub_stats":[{"stat":"def%","value":3.1}],"id":"c2056b20-3096-4bc4-9f92-d91c97312fe9"},{"rarity":3,"type":"Circlet of Logos","main_stat":"atk%","sub_stats":[{"stat":"crit rate%","value":2.3}],"id":"1465928c-0e77-4fcb-affa-b6eae4abc4a3"},{"rarity":3,"type":"Sands of Eon","main_stat":"atk%","sub_stats":[{"stat":"def","value":8}],"id":"6605ed00-ce97-404c-96e4-66610a0d8f3e"},{"rarity":3,"type":"Goblet of Eonothem","main_stat":"atk%","sub_stats":[{"stat":"atk","value":9}],"id":"8003ac8c-e23b-4125-8e22-2989d4bf61bc"},{"rarity":3,"type":"Plume of Death","main_stat":"atk","sub_stats":[{"stat":"crit dmg%","value":3.3}],"id":"bb9d7732-b1e9-4135-81ce-e0421def69e9"},{"rarity":3,"type":"Circlet of Logos","main_stat":"def%","sub_stats":[{"stat":"crit dmg%","value":3.7}],"id":"48041ff0-c695-4448-9057-474626a303eb"},{"rarity":3,"type":"Circlet of Logos","main_stat":"def%","sub_stats":[{"stat":"def","value":10}],"id":"bec07c72-1594-4974-846b-a75cf31f397a"}]},{"description":"recharge","type":"condensed","id":"e6839dff-b357-46b4-9c70-b82db67ecb82","created":"Sat Feb 05 2022 20:34:51 GMT-0500","artifacts":[{"rarity":5,"type":"Goblet of Eonothem","main_stat":"elemental dmg bonus%","sub_stats":[{"stat":"atk","value":18},{"stat":"def%","value":5.8},{"stat":"elemental mastery","value":19}],"id":"b7af6e16-1bdf-4b3c-8352-e17f90fbdd30"},{"rarity":5,"type":"Goblet of Eonothem","main_stat":"def%","sub_stats":[{"stat":"crit dmg%","value":7.8},{"stat":"atk","value":19},{"stat":"crit rate%","value":3.9},{"stat":"hp","value":299}],"id":"8cc9de1e-bf19-4651-893e-ccca3cd1c48d"},{"rarity":4,"type":"Goblet of Eonothem","main_stat":"def%","sub_stats":[{"stat":"elemental mastery","value":17},{"stat":"atk","value":12},{"stat":"atk%","value":3.3}],"id":"cdfd7f2c-4e2f-4af3-bc7d-1d23900d1a0b"},{"rarity":4,"type":"Plume of Death","main_stat":"atk","sub_stats":[{"stat":"energy recharge","value":5.2},{"stat":"atk%","value":4.2}],"id":"8dfc51a4-132e-4247-9225-c74c6f7f8a3d"},{"rarity":4,"type":"Circlet of Logos","main_stat":"hp%","sub_stats":[{"stat":"hp","value":167},{"stat":"atk","value":14}],"id":"b588b274-8b33-4397-af17-677e0429a3ad"},{"rarity":4,"type":"Flower of Life","main_stat":"hp","sub_stats":[{"stat":"def","value":17},{"stat":"crit rate%","value":2.8}],"id":"2a1853d4-03c6-44e2-b1c7-52dc9dd57f66"},{"rarity":4,"type":"Flower of Life","main_stat":"hp","sub_stats":[{"stat":"elemental mastery","value":13},{"stat":"energy recharge","value":4.1}],"id":"ca1c1005-f039-43ea-a70f-454aa0f2bc1e"},{"rarity":4,"type":"Circlet of Logos","main_stat":"elemental mastery","sub_stats":[{"stat":"atk","value":12},{"stat":"def%","value":5.3}],"id":"9f163276-b4d8-41bb-a209-b6797c5dea3e"},{"rarity":3,"type":"Flower of Life","main_stat":"hp","sub_stats":[{"stat":"def%","value":3.5}],"id":"722eacdc-6fa2-4ba0-b725-7fd2cb5f7db8"},{"rarity":3,"type":"Sands of Eon","main_stat":"elemental mastery","sub_stats":[{"stat":"atk","value":8}],"id":"8ac13ad4-57e2-487a-9fef-26064a4332ae"},{"rarity":3,"type":"Sands of Eon","main_stat":"def%","sub_stats":[{"stat":"crit dmg%","value":4.7}],"id":"d024c9a0-e9ed-489f-8377-bf49ec25f78b"},{"rarity":3,"type":"Plume of Death","main_stat":"atk","sub_stats":[{"stat":"def","value":9}],"id":"a04c82d9-87d5-4380-91ac-3d73b797a7ac"},{"rarity":3,"type":"Circlet of Logos","main_stat":"def%","sub_stats":[{"stat":"crit rate%","value":1.6},{"stat":"hp","value":100}],"id":"e3fdbe56-4349-408f-abae-da1c515c2e39"},{"rarity":3,"type":"Sands of Eon","main_stat":"hp%","sub_stats":[{"stat":"energy recharge","value":3.9}],"id":"ac70ba54-cbe0-49be-ab27-50bc46745597"},{"rarity":3,"type":"Sands of Eon","main_stat":"hp%","sub_stats":[{"stat":"atk","value":7}],"id":"37f2bbfa-23da-47bc-bf51-4f137e7c5c3f"}]},{"description":"recharge","type":"condensed","id":"726ac26f-10a3-4d5d-a22a-dfe8a1d75add","created":"Sat Feb 05 2022 21:00:19 GMT-0500","artifacts":[{"rarity":5,"type":"Plume of Death","main_stat":"atk","sub_stats":[{"stat":"crit rate%","value":3.1},{"stat":"def","value":16},{"stat":"atk%","value":5.8}],"id":"3ba95825-586c-4b4c-b94f-4bedc2a65eaf"},{"rarity":5,"type":"Goblet of Eonothem","main_stat":"def%","sub_stats":[{"stat":"atk","value":19},{"stat":"atk%","value":5.3},{"stat":"hp%","value":4.7}],"id":"81c860bf-242d-419d-af6d-b6f035bda943"},{"rarity":4,"type":"Sands of Eon","main_stat":"def%","sub_stats":[{"stat":"hp%","value":4.2},{"stat":"hp","value":215}],"id":"fa476eed-73c2-4873-b6a1-6f0470699f64"},{"rarity":4,"type":"Goblet of Eonothem","main_stat":"hp%","sub_stats":[{"stat":"atk","value":11},{"stat":"crit rate%","value":3.1},{"stat":"def","value":17}],"id":"b775ace8-d564-41d7-a998-ae6622adcff0"},{"rarity":4,"type":"Goblet of Eonothem","main_stat":"elemental dmg bonus%","sub_stats":[{"stat":"crit rate%","value":2.2},{"stat":"def","value":17},{"stat":"elemental mastery","value":15}],"id":"8d52da94-e120-47b7-8da2-932869acd788"},{"rarity":4,"type":"Plume of Death","main_stat":"atk","sub_stats":[{"stat":"elemental mastery","value":19},{"stat":"def","value":13}],"id":"90f41bf2-32b4-4a58-b823-e10c09d62038"},{"rarity":4,"type":"Flower of Life","main_stat":"hp","sub_stats":[{"stat":"atk%","value":4.2},{"stat":"energy recharge","value":4.7}],"id":"887af33c-c05c-4673-aaa1-56103a27c96f"},{"rarity":3,"type":"Goblet of Eonothem","main_stat":"def%","sub_stats":[{"stat":"hp%","value":3.2},{"stat":"atk","value":8}],"id":"c2d3725d-9feb-4845-87d9-220db2988b7c"},{"rarity":3,"type":"Flower of Life","main_stat":"hp","sub_stats":[{"stat":"atk","value":7}],"id":"f4639dcc-25a2-45d8-9e1c-8d1c01cc90d0"},{"rarity":3,"type":"Flower of Life","main_stat":"hp","sub_stats":[{"stat":"def","value":8}],"id":"95f1d7d2-9c1d-4ce6-8e58-a9e1bc6c49d7"},{"rarity":3,"type":"Plume of Death","main_stat":"atk","sub_stats":[{"stat":"def","value":8}],"id":"f0dc905c-0f11-4ade-93a2-ecd96a99f7cc"},{"rarity":3,"type":"Circlet of Logos","main_stat":"atk%","sub_stats":[{"stat":"hp","value":100},{"stat":"crit dmg%","value":3.7}],"id":"ea56c602-55da-4f52-8c99-813629d9bd81"},{"rarity":3,"type":"Sands of Eon","main_stat":"hp%","sub_stats":[{"stat":"elemental mastery","value":13}],"id":"6483d612-659e-4fec-9d48-711008cd1c04"}]},{"description":"recharge","type":"20","id":"bb29b6ae-e63f-4480-a438-5d082f4c447e","created":"Sat Feb 05 2022 21:04:18 GMT-0500","artifacts":[{"rarity":5,"type":"Sands of Eon","main_stat":"def%","sub_stats":[{"stat":"hp","value":299},{"stat":"energy recharge","value":4.5},{"stat":"hp%","value":4.1}],"id":"9fb5d1d2-7e91-4fa4-8958-3be2d66aa8e8"},{"rarity":4,"type":"Sands of Eon","main_stat":"hp%","sub_stats":[{"stat":"elemental mastery","value":19},{"stat":"atk","value":12}],"id":"35ebfdca-8fd4-43f0-b953-757632b54980"},{"rarity":4,"type":"Sands of Eon","main_stat":"energy recharge","sub_stats":[{"stat":"crit rate%","value":2.5},{"stat":"atk","value":11}],"id":"90f7710d-2153-4189-b22e-85c8db28e2e1"},{"rarity":3,"type":"Plume of Death","main_stat":"atk","sub_stats":[{"stat":"atk%","value":3.5},{"stat":"elemental mastery","value":13}],"id":"59d26211-ccba-4c27-a3fc-888b1ac8a1af"},{"rarity":3,"type":"Plume of Death","main_stat":"atk","sub_stats":[{"stat":"def","value":9}],"id":"5341d466-bff7-4207-80ec-5190bdf08c67"},{"rarity":3,"type":"Sands of Eon","main_stat":"energy recharge","sub_stats":[{"stat":"def","value":11}],"id":"32ca4e70-3833-496e-88ec-a7aa44cb4f02"},{"rarity":3,"type":"Goblet of Eonothem","main_stat":"hp%","sub_stats":[{"stat":"hp","value":115}],"id":"d1720b6d-6d3e-48d2-b378-384fd08a4572"}]}]