[{"id":"eb607eea-428c-4681-961d-d79214116043","created":"Sun Jan 02 2022 18:52:14 GMT-0500 (Eastern Standard Time)","description":"heal","type":"20","artifacts":[{"artifact_rarity":5,"artifact_type":"Circlet of Logos","main_stat":"crit rate%","sub_stats":[{"name":"def","value":21},{"name":"hp","value":209},{"name":"atk","value":16}],"id":"8e35977d-d1a0-4e8d-9e41-3d9bed774784"},{"artifact_rarity":4,"artifact_type":"Plume of Death","main_stat":"atk","sub_stats":[{"name":"def","value":17},{"name":"energy recharge","value":4.1}],"id":"0e047a78-4992-4a54-91b0-0eb6267ba5f3"},{"artifact_rarity":4,"artifact_type":"Plume of Death","main_stat":"atk","sub_stats":[{"name":"def","value":19},{"name":"def%","value":4.7}],"id":"46bec791-e576-45dc-92e3-bfe5036e2808"},{"artifact_rarity":4,"artifact_type":"Circlet of Logos","main_stat":"def%","sub_stats":[{"name":"hp","value":167},{"name":"atk%","value":3.7}],"id":"6d108f07-c2a9-4e47-821a-99010dbbda2c"},{"artifact_rarity":3,"artifact_type":"Goblet of Eonothem","main_stat":"def%","sub_stats":[{"name":"hp%","value":2.5}],"id":"a5a6d814-0678-4d87-b0ef-5eb77415a0a2"},{"artifact_rarity":3,"artifact_type":"Circlet of Logos","main_stat":"hp%","sub_stats":[{"name":"atk","value":9}],"id":"71effdb6-1eba-4953-b803-95b43ab01669"},{"artifact_rarity":3,"artifact_type":"Sands of Eon","main_stat":"atk%","sub_stats":[{"name":"hp%","value":2.8}],"id":"056f87a8-eef9-46d6-8371-1911de54fe47"},{"artifact_rarity":3,"artifact_type":"Goblet of Eonothem","main_stat":"def%","sub_stats":[{"name":"hp%","value":3.5}],"id":"8f63d95d-1db0-4893-b043-35656b0760ab"}]},{"id":"9c08c101-9182-44d8-9a66-5d2f1f62d1f8","created":"Sun Jan 02 2022 18:56:12 GMT-0500 (Eastern Standard Time)","description":"heal","type":"condensed","artifacts":[{"artifact_rarity":5,"artifact_type":"Goblet of Eonothem","main_stat":"def%","sub_stats":[{"name":"hp","value":299},{"name":"atk","value":14},{"name":"def","value":21}],"id":"63c9aaae-d5a3-46fe-b790-d8477859c87b"},{"artifact_rarity":5,"artifact_type":"Circlet of Logos","main_stat":"hp%","sub_stats":[{"name":"def%","value":5.1},{"name":"energy recharge","value":4.5},{"name":"elemental mastery","value":16}],"id":"59c2505d-3d86-4daf-a355-d97035c97613"},{"artifact_rarity":5,"artifact_type":"Flower of Life","main_stat":"hp","sub_stats":[{"name":"crit dmg%","value":6.2},{"name":"atk","value":19},{"name":"def","value":19},{"name":"elemental mastery","value":19}],"id":"e40f2dfc-5afb-4ab8-93fd-12bc165ad9e9"},{"artifact_rarity":4,"artifact_type":"Goblet of Eonothem","main_stat":"physical dmg bonus%","sub_stats":[{"name":"atk%","value":4.7},{"name":"elemental mastery","value":19}],"id":"d00dfeb7-3728-404c-8526-09584054cbfe"},{"artifact_rarity":4,"artifact_type":"Circlet of Logos","main_stat":"def%","sub_stats":[{"name":"def","value":15},{"name":"energy recharge","value":4.1}],"id":"1947e2ef-bc1f-4829-abc1-aa521d5fba33"},{"artifact_rarity":4,"artifact_type":"Flower of Life","main_stat":"hp","sub_stats":[{"name":"elemental mastery","value":19},{"name":"def","value":19},{"name":"atk","value":16}],"id":"6e160e57-ef64-46f1-baee-de8989255ec0"},{"artifact_rarity":4,"artifact_type":"Sands of Eon","main_stat":"def%","sub_stats":[{"name":"energy recharge","value":3.6},{"name":"crit rate%","value":2.8},{"name":"hp","value":215}],"id":"53339e89-f482-4150-8bdc-fd14e18155f2"},{"artifact_rarity":4,"artifact_type":"Sands of Eon","main_stat":"hp%","sub_stats":[{"name":"atk%","value":3.3},{"name":"crit dmg%","value":5},{"name":"hp","value":215}],"id":"f534b04b-a0b0-4d84-9f58-32b4506cbf73"},{"artifact_rarity":3,"artifact_type":"Goblet of Eonothem","main_stat":"elemental dmg bonus%","sub_stats":[{"name":"crit rate%","value":2.3}],"id":"ff9e3698-05ff-4215-b257-415ac47eab2a"},{"artifact_rarity":3,"artifact_type":"Plume of Death","main_stat":"atk","sub_stats":[{"name":"def%","value":4.4}],"id":"622d3bb7-946e-4bde-9a18-6aa038a97e23"},{"artifact_rarity":3,"artifact_type":"Circlet of Logos","main_stat":"def%","sub_stats":[{"name":"atk%","value":3.5}],"id":"90c07cdd-96a2-490a-9549-8faed11a5aa2"},{"artifact_rarity":3,"artifact_type":"Flower of Life","main_stat":"hp","sub_stats":[{"name":"hp%","value":2.5}],"id":"06bcb07b-39f3-411f-a31a-4793f3e4f1eb"},{"artifact_rarity":3,"artifact_type":"Goblet of Eonothem","main_stat":"elemental dmg bonus%","sub_stats":[{"name":"def","value":10}],"id":"79a33eb6-4d20-43c7-8463-dda7c702b63e"},{"artifact_rarity":3,"artifact_type":"Plume of Death","main_stat":"atk","sub_stats":[{"name":"def","value":8}],"id":"b92b9455-fd72-48c4-b2c1-62ddb5699ea4"},{"artifact_rarity":3,"artifact_type":"Flower of Life","main_stat":"hp","sub_stats":[{"name":"atk%","value":3.2},{"name":"def%","value":3.1}],"id":"1950f59c-fa0a-4ee8-9129-b988d9c4046c"},{"artifact_rarity":3,"artifact_type":"Sands of Eon","main_stat":"atk%","sub_stats":[{"name":"def","value":9},{"name":"def%","value":3.9}],"id":"3bb72633-82cd-43cb-b40c-9aecd86dafcb"}]},{"id":"8f908f10-1b57-4f16-90c1-40839157b07e","created":"Sun Jan 02 2022 19:00:42 GMT-0500 (Eastern Standard Time)","description":"heal","type":"condensed","artifacts":[{"artifact_rarity":5,"artifact_type":"Sands of Eon","main_stat":"atk%","sub_stats":[{"name":"atk","value":19},{"name":"def","value":19},{"name":"crit dmg%","value":6.2}],"id":"29626600-17b5-446d-8f9f-bd5c9fda685b"},{"artifact_rarity":5,"artifact_type":"Sands of Eon","main_stat":"atk%","sub_stats":[{"name":"hp","value":239},{"name":"crit dmg%","value":5.4},{"name":"elemental mastery","value":19}],"id":"f0539291-1974-417c-9b66-23ca93e540db"},{"artifact_rarity":4,"artifact_type":"Circlet of Logos","main_stat":"hp%","sub_stats":[{"name":"atk%","value":4.2},{"name":"atk","value":12},{"name":"energy recharge","value":4.1}],"id":"584e78fc-3790-430b-8c55-98d115b7d269"},{"artifact_rarity":4,"artifact_type":"Circlet of Logos","main_stat":"atk%","sub_stats":[{"name":"elemental mastery","value":17},{"name":"def","value":19},{"name":"hp%","value":4.7}],"id":"130d6c65-7dd8-4559-86c2-f258fdce690b"},{"artifact_rarity":4,"artifact_type":"Goblet of Eonothem","main_stat":"hp%","sub_stats":[{"name":"atk%","value":4.7},{"name":"crit dmg%","value":5}],"id":"76f107b9-af68-43ae-bf4c-70dc0e297476"},{"artifact_rarity":4,"artifact_type":"Goblet of Eonothem","main_stat":"elemental dmg bonus%","sub_stats":[{"name":"def","value":17},{"name":"energy recharge","value":4.1}],"id":"e9034c15-b898-427a-924a-c05dd13e971d"},{"artifact_rarity":4,"artifact_type":"Goblet of Eonothem","main_stat":"def%","sub_stats":[{"name":"crit rate%","value":2.8},{"name":"hp","value":191},{"name":"energy recharge","value":4.1}],"id":"463ba7d0-fcf2-4fd3-84c9-3806db5dc8b3"},{"artifact_rarity":3,"artifact_type":"Goblet of Eonothem","main_stat":"hp%","sub_stats":[{"name":"hp","value":129},{"name":"def%","value":3.5}],"id":"8aa77335-386b-413e-a949-857a8e38605a"},{"artifact_rarity":3,"artifact_type":"Circlet of Logos","main_stat":"crit rate%","sub_stats":[{"name":"def%","value":3.9}],"id":"3d0771ce-af6f-41f7-8864-9930d3d18c88"},{"artifact_rarity":3,"artifact_type":"Circlet of Logos","main_stat":"hp%","sub_stats":[{"name":"elemental mastery","value":14}],"id":"1b723f85-e5a8-4842-b825-cf23526e78ad"},{"artifact_rarity":3,"artifact_type":"Goblet of Eonothem","main_stat":"elemental dmg bonus%","sub_stats":[{"name":"hp%","value":2.8},{"name":"atk%","value":2.8}],"id":"0ccf97e2-230a-4827-a238-1625edbf3ac0"},{"artifact_rarity":3,"artifact_type":"Circlet of Logos","main_stat":"hp%","sub_stats":[{"name":"crit dmg%","value":4.7}],"id":"93291ec8-3251-4008-9fb2-1b2e95550d50"},{"artifact_rarity":3,"artifact_type":"Flower of Life","main_stat":"hp","sub_stats":[{"name":"def","value":10}],"id":"cf06d729-2f62-4a38-ad92-325711ded498"}]},{"id":"8b7d90aa-3620-495d-93ae-343bf96b88d1","created":"Sun Jan 02 2022 19:05:06 GMT-0500 (Eastern Standard Time)","description":"heal","type":"condensed","artifacts":[{"artifact_rarity":5,"artifact_type":"Plume of Death","main_stat":"atk","sub_stats":[{"name":"elemental mastery","value":19},{"name":"hp","value":269},{"name":"def","value":21},{"name":"energy recharge","value":5.2}],"id":"d1663a9a-1470-45d7-a3ea-3088031b4450"},{"artifact_rarity":5,"artifact_type":"Sands of Eon","main_stat":"energy recharge","sub_stats":[{"name":"hp","value":269},{"name":"atk","value":14},{"name":"def","value":19},{"name":"crit rate%","value":3.9}],"id":"17d545e1-fcfe-4d63-988c-899e0a839016"},{"artifact_rarity":4,"artifact_type":"Goblet of Eonothem","main_stat":"elemental dmg bonus%","sub_stats":[{"name":"energy recharge","value":4.1},{"name":"crit rate%","value":2.8}],"id":"bd9079a0-e5e8-44f5-ac7e-ac03f92af97a"},{"artifact_rarity":4,"artifact_type":"Plume of Death","main_stat":"atk","sub_stats":[{"name":"crit dmg%","value":5.6},{"name":"elemental mastery","value":13}],"id":"dfdba2bc-4cc2-48d3-a96a-9578fcffc9b6"},{"artifact_rarity":4,"artifact_type":"Circlet of Logos","main_stat":"def%","sub_stats":[{"name":"def","value":17},{"name":"elemental mastery","value":13},{"name":"atk","value":16}],"id":"46172df8-d74f-4cf0-bedb-d9f576be135c"},{"artifact_rarity":4,"artifact_type":"Goblet of Eonothem","main_stat":"elemental dmg bonus%","sub_stats":[{"name":"hp%","value":4.2},{"name":"hp","value":167}],"id":"b2f7628a-0a13-409a-9a00-6bb6f206db74"},{"artifact_rarity":4,"artifact_type":"Plume of Death","main_stat":"atk","sub_stats":[{"name":"crit dmg%","value":5},{"name":"hp","value":239}],"id":"ef793889-a70f-48f5-a6eb-08923ecafa84"},{"artifact_rarity":3,"artifact_type":"Goblet of Eonothem","main_stat":"elemental dmg bonus%","sub_stats":[{"name":"def%","value":3.1}],"id":"91dcb91f-167a-4d93-81d1-150e3c8cc3f1"},{"artifact_rarity":3,"artifact_type":"Plume of Death","main_stat":"atk","sub_stats":[{"name":"atk%","value":2.5}],"id":"77f06335-e985-4a79-b234-5c533bfced24"},{"artifact_rarity":3,"artifact_type":"Sands of Eon","main_stat":"hp%","sub_stats":[{"name":"energy recharge","value":2.7}],"id":"af505796-116e-484b-b6d3-84e31cdc29cf"},{"artifact_rarity":3,"artifact_type":"Plume of Death","main_stat":"atk","sub_stats":[{"name":"crit rate%","value":1.6},{"name":"def%","value":3.1}],"id":"d79b8786-cf07-4654-a208-4aa4add0e16d"},{"artifact_rarity":3,"artifact_type":"Circlet of Logos","main_stat":"hp%","sub_stats":[{"name":"atk%","value":2.8}],"id":"8d16c2fa-654d-44b0-a089-a40ce40f4130"},{"artifact_rarity":3,"artifact_type":"Sands of Eon","main_stat":"hp%","sub_stats":[{"name":"atk","value":7}],"id":"62fd39a9-22ed-473e-a04c-62f7346f90e7"}]},{"id":"656dd948-c9d3-442a-aa91-5f65830ee1b0","created":"Sun Jan 02 2022 19:10:37 GMT-0500 (Eastern Standard Time)","description":"heal","type":"condensed","artifacts":[{"artifact_rarity":5,"artifact_type":"Sands of Eon","main_stat":"energy recharge","sub_stats":[{"name":"def","value":16},{"name":"atk","value":19},{"name":"elemental mastery","value":19},{"name":"atk%","value":5.8}],"id":"c16bb274-20d2-4817-bb26-d2f4fa80b063"},{"artifact_rarity":5,"artifact_type":"Circlet of Logos","main_stat":"def%","sub_stats":[{"name":"atk","value":14},{"name":"hp%","value":4.1},{"name":"def","value":23}],"id":"fd966706-8d06-4748-817b-0d23dd819504"},{"artifact_rarity":5,"artifact_type":"Flower of Life","main_stat":"hp","sub_stats":[{"name":"atk","value":18},{"name":"elemental mastery","value":23},{"name":"def%","value":5.8}],"id":"2a0b4389-44a4-4b8f-bbce-6a80a5b12c64"},{"artifact_rarity":4,"artifact_type":"Goblet of Eonothem","main_stat":"def%","sub_stats":[{"name":"crit rate%","value":2.5}],"id":"fb8e4eb6-e711-44e6-8f22-324c8d376aa6"},{"artifact_rarity":4,"artifact_type":"Sands of Eon","main_stat":"hp%","sub_stats":[{"name":"def","value":15},{"name":"crit dmg%","value":4.4}],"id":"eead7a91-d4c1-48e1-9d0f-11b76c9ca6b7"},{"artifact_rarity":4,"artifact_type":"Goblet of Eonothem","main_stat":"def%","sub_stats":[{"name":"elemental mastery","value":17},{"name":"hp","value":167}],"id":"2d5943a9-6e3e-48c3-bccb-a827e1cff8c0"},{"artifact_rarity":4,"artifact_type":"Goblet of Eonothem","main_stat":"elemental dmg bonus%","sub_stats":[{"name":"hp%","value":3.3},{"name":"def%","value":4.7}],"id":"ba387928-3939-41cd-9758-eb79fc45a29e"},{"artifact_rarity":4,"artifact_type":"Plume of Death","main_stat":"atk","sub_stats":[{"name":"hp","value":191},{"name":"atk%","value":3.7}],"id":"22376244-e32e-4ca4-b094-92d97aaadbe2"},{"artifact_rarity":4,"artifact_type":"Flower of Life","main_stat":"hp","sub_stats":[{"name":"energy recharge","value":5.2},{"name":"atk%","value":3.3}],"id":"5f57cfa2-6ba6-43d2-871a-782f02cd341e"},{"artifact_rarity":3,"artifact_type":"Goblet of Eonothem","main_stat":"hp%","sub_stats":[{"name":"def%","value":3.9}],"id":"6805452a-3fcd-4374-b615-856ddc082b74"},{"artifact_rarity":3,"artifact_type":"Plume of Death","main_stat":"atk","sub_stats":[{"name":"crit dmg%","value":3.7}],"id":"c15d8009-d388-4d9c-9305-e360ef63cf19"},{"artifact_rarity":3,"artifact_type":"Circlet of Logos","main_stat":"crit dmg%","sub_stats":[{"name":"energy recharge","value":3.5},{"name":"def","value":10}],"id":"58b53deb-2fd9-44f1-b631-1480cccb1891"},{"artifact_rarity":3,"artifact_type":"Flower of Life","main_stat":"hp","sub_stats":[{"name":"hp%","value":3.2}],"id":"6fa1aac7-78eb-475e-b13d-b8e8c6d4b587"},{"artifact_rarity":3,"artifact_type":"Goblet of Eonothem","main_stat":"elemental dmg bonus%","sub_stats":[{"name":"crit rate%","value":2.3}],"id":"af063a92-8220-4c44-9b5d-c961f2312772"},{"artifact_rarity":3,"artifact_type":"Flower of Life","main_stat":"hp","sub_stats":[{"name":"energy recharge","value":3.5},{"name":"atk%","value":3.2}],"id":"b1c15209-2893-48c7-ba71-d787dbc4bc25"}]}]